{"tweet":"started remembering my dreams again, but good go the nigtmares have been awful ","hiddentargetclue":0,"arrived_key":"2020-01-27 21:42:04.211 - 23156","timestamp":"2020-01-27T23:42:04.211Z"}
{"tweet":"@MissHollyHocks That is a wonderful idea, if only ","hiddentargetclue":0,"arrived_key":"2020-01-27 21:42:04.211 - 31715","timestamp":"2020-01-27T23:42:04.211Z"}
{"tweet":"Listening to KoL before work. Hoping it will psyche me up to go in on such a sunny day. It is doing the opposite... ","hiddentargetclue":0,"arrived_key":"2020-01-27 21:42:04.211 - 57436","timestamp":"2020-01-27T23:42:04.211Z"}
{"tweet":"#SanctuarySunday @sez101 yeah I know, saw a bit of one of the bodies left over in the aquarium, not nice, I love those little dudes ","hiddentargetclue":0,"arrived_key":"2020-01-27 21:42:04.211 - 83972","timestamp":"2020-01-27T23:42:04.211Z"}
{"tweet":"i had a dream i got my tragus pierced...i now want it more than ever ","hiddentargetclue":0,"arrived_key":"2020-01-27 21:42:04.211 - 19883","timestamp":"2020-01-27T23:42:04.211Z"}
{"tweet":"Up....too early  best hav a productive day now...","hiddentargetclue":0,"arrived_key":"2020-01-27 21:42:04.211 - 31196","timestamp":"2020-01-27T23:42:04.211Z"}
{"tweet":"I suck...   ","hiddentargetclue":0,"arrived_key":"2020-01-27 21:42:04.211 - 50017","timestamp":"2020-01-27T23:42:04.211Z"}
{"tweet":"I'm also still keeping my head above all the rain that's been falling in the past two weeks. ","hiddentargetclue":0,"arrived_key":"2020-01-27 21:42:04.211 - 61792","timestamp":"2020-01-27T23:42:04.211Z"}
{"tweet":"just bought miller high life, hungry man dinners, and a bottle of lube. you win life, you win.  kidding about the lube...","hiddentargetclue":0,"arrived_key":"2020-01-27 21:42:04.211 - 62242","timestamp":"2020-01-27T23:42:04.211Z"}
{"tweet":"Uh oh... I'm not feeling well ","hiddentargetclue":0,"arrived_key":"2020-01-27 21:42:04.211 - 64632","timestamp":"2020-01-27T23:42:04.211Z"}
{"tweet":"@AnindithoDimas @tieshadiona kalian hobby banget sih nge blip? emang seru yaa ? gue masiih gak nangkep  props, listener gitu2 apa sih ? ","hiddentargetclue":0,"arrived_key":"2020-01-27 21:42:04.211 - 72169","timestamp":"2020-01-27T23:42:04.211Z"}
{"tweet":"@keLee random suprising time AND special days. I'm greedy that way ","hiddentargetclue":1,"arrived_key":"2020-01-27 21:42:04.211 - 82842","timestamp":"2020-01-27T23:42:04.211Z"}
{"tweet":"I'm at my favorite hang out place but the wi-fi connection is not working.  Good thing I brought the prepaid internet connection with me ","hiddentargetclue":1,"arrived_key":"2020-01-27 21:42:04.211 - 95631","timestamp":"2020-01-27T23:42:04.211Z"}
{"tweet":"Hello to @hgtvpro, our 700th follower! And they're part of the media, so even better! ","hiddentargetclue":1,"arrived_key":"2020-01-27 21:42:04.211 - 10259","timestamp":"2020-01-27T23:42:04.211Z"}
{"tweet":"i love warm days like this.. especially for laying out  dinner, blockbuster, movie night with wifey.. such a good day ","hiddentargetclue":1,"arrived_key":"2020-01-27 21:42:04.211 - 11303","timestamp":"2020-01-27T23:42:04.211Z"}
{"tweet":"Am now working on autograph cards for Miss OK. She is a meteorology student at OU. She wants to keep us all safe from storms! ","hiddentargetclue":1,"arrived_key":"2020-01-27 21:42:04.211 - 12375","timestamp":"2020-01-27T23:42:04.211Z"}
{"tweet":"Exam went well, who knew i could do chemistry  Henry Homesweet! is a genius!!! xD","hiddentargetclue":1,"arrived_key":"2020-01-27 21:42:04.211 - 13372","timestamp":"2020-01-27T23:42:04.211Z"}
{"tweet":"@davidrsheehan my pleasure  hope it helps. doing great! thanks for checking","hiddentargetclue":1,"arrived_key":"2020-01-27 21:42:04.211 - 13469","timestamp":"2020-01-27T23:42:04.211Z"}
{"tweet":"is actually in love with nick jonas ","hiddentargetclue":1,"arrived_key":"2020-01-27 21:42:04.211 - 14090","timestamp":"2020-01-27T23:42:04.211Z"}
{"tweet":"@charlotteord hey kid you have a new member who has posted on your kettlebell blog ","hiddentargetclue":1,"arrived_key":"2020-01-27 21:42:04.211 - 14206","timestamp":"2020-01-27T23:42:04.211Z"}
{"tweet":"Made it to the apartment. Good to see Lindy again. ","hiddentargetclue":1,"arrived_key":"2020-01-27 21:42:04.211 - 14950","timestamp":"2020-01-27T23:42:04.211Z"}
{"tweet":"@sha0359 course ill follow you, ill follow you wherever you like! ","hiddentargetclue":1,"arrived_key":"2020-01-27 21:42:04.211 - 15371","timestamp":"2020-01-27T23:42:04.211Z"}
{"tweet":"@NikkiFitness just ordered BOOTY CAMP! Can't wait for it to arrive. ","hiddentargetclue":1,"arrived_key":"2020-01-27 21:42:04.211 - 15692","timestamp":"2020-01-27T23:42:04.211Z"}
{"tweet":"HIIIIIIIIIIII!!!!!  Back to Stuart today","hiddentargetclue":1,"arrived_key":"2020-01-27 21:42:04.211 - 15919","timestamp":"2020-01-27T23:42:04.211Z"}
