{"tweet":"@sockcreature What happened? And sorry I couldn't come..left right after you sent the first message and didn't see the other til got back ","hiddentargetclue":0,"arrived_key":"2020-01-27 21:58:27.076 - 19315","timestamp":"2020-01-27T23:58:27.076Z"}
{"tweet":"i need to get a life  two more days till freedom   (for all my loyal followers in two days you will get more updates )","hiddentargetclue":0,"arrived_key":"2020-01-27 21:58:27.076 - 51617","timestamp":"2020-01-27T23:58:27.076Z"}
{"tweet":"@spencerpratt aww spencer I called all the way from Australia and got your voicemail  ","hiddentargetclue":0,"arrived_key":"2020-01-27 21:58:27.076 - 13165","timestamp":"2020-01-27T23:58:27.076Z"}
{"tweet":"feelin like shit ","hiddentargetclue":0,"arrived_key":"2020-01-27 21:58:27.076 - 15076","timestamp":"2020-01-27T23:58:27.076Z"}
{"tweet":"CRYING CUZ PEOPLE WONT FOLLOW ME!!!!!!! ","hiddentargetclue":0,"arrived_key":"2020-01-27 21:58:27.076 - 17514","timestamp":"2020-01-27T23:58:27.076Z"}
{"tweet":"@jobadge just be greatful you're not moving to Moodle! ","hiddentargetclue":0,"arrived_key":"2020-01-27 21:58:27.076 - 34210","timestamp":"2020-01-27T23:58:27.076Z"}
{"tweet":"I wrote a sizeable post about amazing Scribblenauts is and now I can't post it.  OTOH, Joystiq had a ten word challenge to vex the game.","hiddentargetclue":0,"arrived_key":"2020-01-27 21:58:27.076 - 38502","timestamp":"2020-01-27T23:58:27.076Z"}
{"tweet":"@faiznurdavid oh yes, i read it.  sedih la. or maybe he can join us later. soh nya mbak kita g beach. or maybe not.","hiddentargetclue":0,"arrived_key":"2020-01-27 21:58:27.076 - 51748","timestamp":"2020-01-27T23:58:27.076Z"}
{"tweet":"@wizardgold Thanks for the advice! I'm mostly happy with GnuCash, being free and open source. Just means i need the other computer! ","hiddentargetclue":1,"arrived_key":"2020-01-27 21:58:27.076 - 83578","timestamp":"2020-01-27T23:58:27.076Z"}
{"tweet":"Going to a dinner at a professor's place. ","hiddentargetclue":1,"arrived_key":"2020-01-27 21:58:27.076 - 92933","timestamp":"2020-01-27T23:58:27.076Z"}
{"tweet":"@DesertTwitch arm is fine.  No more physical therapy, unless you count bike riding ","hiddentargetclue":1,"arrived_key":"2020-01-27 21:58:27.076 - 10482","timestamp":"2020-01-27T23:58:27.076Z"}
{"tweet":"watching Family Guy. Stewie is planning for world domination! Brian is with him! ","hiddentargetclue":1,"arrived_key":"2020-01-27 21:58:27.076 - 12697","timestamp":"2020-01-27T23:58:27.076Z"}
{"tweet":"@lilylauren i think cassiedog is thinking about eating @andrewsayer for dessert ","hiddentargetclue":1,"arrived_key":"2020-01-27 21:58:27.076 - 12867","timestamp":"2020-01-27T23:58:27.076Z"}
{"tweet":"If you get the chance go to itunes and click on podcasts see if you find anything familiar. ","hiddentargetclue":1,"arrived_key":"2020-01-27 21:58:27.076 - 14105","timestamp":"2020-01-27T23:58:27.076Z"}
{"tweet":"@dslifton Josh Ritter is awesome I concede. Only on that point though...you and me still have some battling to do. ","hiddentargetclue":1,"arrived_key":"2020-01-27 21:58:27.076 - 14460","timestamp":"2020-01-27T23:58:27.076Z"}
{"tweet":"@doctortips Get 100 followers a day using www.tweeterfollow.com Once you add everyone you are on the train or pay vip ","hiddentargetclue":1,"arrived_key":"2020-01-27 21:58:27.076 - 15430","timestamp":"2020-01-27T23:58:27.076Z"}
{"tweet":"@parhamdoustdar people everywhere are praying for you and hoping the ppl of Tehran are safe. Don't stop believing. Change will come. ","hiddentargetclue":1,"arrived_key":"2020-01-27 21:58:27.076 - 15691","timestamp":"2020-01-27T23:58:27.076Z"}
{"tweet":"@mathemagenic good luck  I wish I could attend your defense,but I have to save days off 4 the school vacation... see you later, I hope","hiddentargetclue":1,"arrived_key":"2020-01-27 21:58:27.076 - 15887","timestamp":"2020-01-27T23:58:27.076Z"}
