{"tweet":"@officialashleyg http://twitpic.com/482y1 - daaaaaamn the crazy person stole MY idea  back to square one....","hiddentargetclue":0,"arrived_key":"2020-01-27 15:50:01.378 - 58606","timestamp":"2020-01-27T15:50:01.378Z"}
{"tweet":"@HeyNiceSweater I just tried to call her. ","hiddentargetclue":0,"arrived_key":"2020-01-27 15:50:01.378 - 15173","timestamp":"2020-01-27T15:50:01.378Z"}
{"tweet":"O myy dayys how is it thatt less pppl are followingg me everydayy??  aahaa :L","hiddentargetclue":0,"arrived_key":"2020-01-27 15:50:01.378 - 19472","timestamp":"2020-01-27T15:50:01.378Z"}
{"tweet":"@isacullen aww i thought you were talking about a mole. ","hiddentargetclue":0,"arrived_key":"2020-01-27 15:50:01.378 - 25494","timestamp":"2020-01-27T15:50:01.378Z"}
{"tweet":"@Spenceh0e Yeah, my legs were screaming. Surprisingly not my knees, which is what I was worried about. Gawd that run was hard ","hiddentargetclue":0,"arrived_key":"2020-01-27 15:50:01.378 - 28009","timestamp":"2020-01-27T15:50:01.378Z"}
{"tweet":"We need to get petrol but just waiting to see if she- owner needs anything else. Dopamine dog aged 12- Bailey. He didn't look good. ","hiddentargetclue":0,"arrived_key":"2020-01-27 15:50:01.378 - 28969","timestamp":"2020-01-27T15:50:01.378Z"}
{"tweet":"Shivering as I wait for train ","hiddentargetclue":0,"arrived_key":"2020-01-27 15:50:01.378 - 34070","timestamp":"2020-01-27T15:50:01.378Z"}
{"tweet":"Just saw a show by Quinn's 1st grade class. It was great! So adorable! My video camera crapped out after 10 minutes (and it was charged) ","hiddentargetclue":0,"arrived_key":"2020-01-27 15:50:01.378 - 36560","timestamp":"2020-01-27T15:50:01.378Z"}
{"tweet":"Anis, my auntie is very worrying you  get well soon okey?","hiddentargetclue":0,"arrived_key":"2020-01-27 15:50:01.378 - 39408","timestamp":"2020-01-27T15:50:01.378Z"}
{"tweet":"made it home (Y) after 6 hours of no standing we made it. home sweet home. but there was a kuffufel with the dog  he's all better now.","hiddentargetclue":0,"arrived_key":"2020-01-27 15:50:01.378 - 41511","timestamp":"2020-01-27T15:50:01.378Z"}
{"tweet":"@rolodaande haha i wanna cuddle with my boyy ","hiddentargetclue":0,"arrived_key":"2020-01-27 15:50:01.378 - 58367","timestamp":"2020-01-27T15:50:01.378Z"}
{"tweet":"I feel like someone is sitting on my chest..  ","hiddentargetclue":0,"arrived_key":"2020-01-27 15:50:01.378 - 68287","timestamp":"2020-01-27T15:50:01.378Z"}
{"tweet":"if I were a car.. not having insurance would give me low self-esteem. ","hiddentargetclue":0,"arrived_key":"2020-01-27 15:50:01.378 - 74920","timestamp":"2020-01-27T15:50:01.378Z"}
{"tweet":"It's annoyingly good weather outside. It taunts me as I stare through the window ","hiddentargetclue":0,"arrived_key":"2020-01-27 15:50:01.378 - 75742","timestamp":"2020-01-27T15:50:01.378Z"}
{"tweet":"completely missed the team lunch today. Staying up till 7am does that ","hiddentargetclue":0,"arrived_key":"2020-01-27 15:50:01.378 - 76302","timestamp":"2020-01-27T15:50:01.378Z"}
{"tweet":"@casmiruknow hehe yulp yulp i will ","hiddentargetclue":1,"arrived_key":"2020-01-27 15:50:01.378 - 82133","timestamp":"2020-01-27T15:50:01.378Z"}
{"tweet":"@Andrew_Johnson OOOHhhh I forgot about the TV show. Ate the chocolate yesterday  Also loved Creamola Foam orange or Cola flavours","hiddentargetclue":1,"arrived_key":"2020-01-27 15:50:01.378 - 92619","timestamp":"2020-01-27T15:50:01.378Z"}
{"tweet":"'Youre gone but yet your mine'.......the romance of that movie  &lt;3","hiddentargetclue":1,"arrived_key":"2020-01-27 15:50:01.378 - 10320","timestamp":"2020-01-27T15:50:01.378Z"}
{"tweet":"time to take a qood hot shower!  lol","hiddentargetclue":1,"arrived_key":"2020-01-27 15:50:01.378 - 14058","timestamp":"2020-01-27T15:50:01.378Z"}
