{"tweet":"@jaydems http://twitpic.com/68p0x - damn that's a cute kitty. i miss mine. ","hiddentargetclue":0,"arrived_key":"2020-01-29 14:45:48.549 - 18979","timestamp":"2020-01-29T16:45:48.549Z"}
{"tweet":"no walking dead until june 10th. ","hiddentargetclue":0,"arrived_key":"2020-01-29 14:45:48.549 - 23776","timestamp":"2020-01-29T16:45:48.549Z"}
{"tweet":"@shesorinchen oh god I hate that. I hate seeing it. Im so sorry ","hiddentargetclue":0,"arrived_key":"2020-01-29 14:45:48.549 - 32433","timestamp":"2020-01-29T16:45:48.549Z"}
{"tweet":"http://twitpic.com/6qe9t - I cut my bangs.  I think I'd rather I hadn't ","hiddentargetclue":0,"arrived_key":"2020-01-29 14:45:48.549 - 38124","timestamp":"2020-01-29T16:45:48.549Z"}
{"tweet":"boring sunday, i wanna read or watch something ","hiddentargetclue":0,"arrived_key":"2020-01-29 14:45:48.549 - 44267","timestamp":"2020-01-29T16:45:48.549Z"}
{"tweet":"@beckysteveyyy glad it made you laugh :L not glad that your feeling ill though ","hiddentargetclue":0,"arrived_key":"2020-01-29 14:45:48.549 - 59760","timestamp":"2020-01-29T16:45:48.549Z"}
{"tweet":"@aschernathan You misunderstand. I didn't really consider the title - was trying to give you a cheering song and a book you might like ","hiddentargetclue":0,"arrived_key":"2020-01-29 14:45:48.549 - 64457","timestamp":"2020-01-29T16:45:48.549Z"}
{"tweet":"@soofehflys a life on the web and twitter ;) you made that too easy xD hahaha how have you been? ","hiddentargetclue":1,"arrived_key":"2020-01-29 14:45:48.549 - 11172","timestamp":"2020-01-29T16:45:48.549Z"}
{"tweet":"listenin to ''ain't i'' ridin through i10 ","hiddentargetclue":1,"arrived_key":"2020-01-29 14:45:48.549 - 14119","timestamp":"2020-01-29T16:45:48.549Z"}
{"tweet":"@catieecahd ok. sure... steal my musical taste. ","hiddentargetclue":1,"arrived_key":"2020-01-29 14:45:48.549 - 14445","timestamp":"2020-01-29T16:45:48.549Z"}
{"tweet":"@ToureKEvelyn My night is good  Watching the game about to eat some crab legs and shrimp ;)","hiddentargetclue":1,"arrived_key":"2020-01-29 14:45:48.549 - 14990","timestamp":"2020-01-29T16:45:48.549Z"}
