{"tweet":"man i am not looking forward to work in the morning. my weekend went by WAY too fast ","hiddentargetclue":0,"arrived_key":"2020-01-27 21:30:56.491 - 29299","timestamp":"2020-01-27T23:30:56.491Z"}
{"tweet":"Looking at Chelly and glad she's in my life. I never want her to grow up but i know it'll happen  lol","hiddentargetclue":0,"arrived_key":"2020-01-27 21:30:56.491 - 84061","timestamp":"2020-01-27T23:30:56.491Z"}
{"tweet":"did any one check new #google #webmaster tool looks.? When i switch off to new look it decreased my links ","hiddentargetclue":0,"arrived_key":"2020-01-27 21:30:56.491 - 10071","timestamp":"2020-01-27T23:30:56.491Z"}
{"tweet":"why He always makes me curious????  i hope we'll meet soon.i love u baby..","hiddentargetclue":0,"arrived_key":"2020-01-27 21:30:56.491 - 11347","timestamp":"2020-01-27T23:30:56.491Z"}
{"tweet":"Im fucking Pissed!, i lost my ID Again :@ not even a month ","hiddentargetclue":0,"arrived_key":"2020-01-27 21:30:56.491 - 29563","timestamp":"2020-01-27T23:30:56.491Z"}
{"tweet":"@thefrontroom Sounds good but I'll be working ","hiddentargetclue":0,"arrived_key":"2020-01-27 21:30:56.491 - 35232","timestamp":"2020-01-27T23:30:56.491Z"}
{"tweet":"@juelzdesignz ahhhhh and why that game is beast mode ","hiddentargetclue":0,"arrived_key":"2020-01-27 21:30:56.491 - 53891","timestamp":"2020-01-27T23:30:56.491Z"}
{"tweet":"@DwightHoward I wish I could go both play taboo and to the parade, but I don't live in Orlando.. I'm MILES away from you. ","hiddentargetclue":0,"arrived_key":"2020-01-27 21:30:56.491 - 63281","timestamp":"2020-01-27T23:30:56.491Z"}
{"tweet":"Ana gets a hoorendous draw. Dokic in the 3rd round and Venus in the 4th. ","hiddentargetclue":0,"arrived_key":"2020-01-27 21:30:56.491 - 64654","timestamp":"2020-01-27T23:30:56.491Z"}
{"tweet":"@supermodeljodi dayumm. U got me beat gotta step my game up ","hiddentargetclue":0,"arrived_key":"2020-01-27 21:30:56.491 - 70085","timestamp":"2020-01-27T23:30:56.491Z"}
{"tweet":"@chrisgwilliams hahaha. I'm driving, so I leave roundabouts when I wake up tomorrow. Arrive proximately 5 hrs from then.  See ya tmw!","hiddentargetclue":1,"arrived_key":"2020-01-27 21:30:56.491 - 91367","timestamp":"2020-01-27T23:30:56.491Z"}
{"tweet":"@boxdog1031 good question   i'm guessing at least 10 years was spent pissing on the floor!","hiddentargetclue":1,"arrived_key":"2020-01-27 21:30:56.491 - 93810","timestamp":"2020-01-27T23:30:56.491Z"}
{"tweet":"@victoria_falls you're sexyyyyy  love you.","hiddentargetclue":1,"arrived_key":"2020-01-27 21:30:56.491 - 96666","timestamp":"2020-01-27T23:30:56.491Z"}
{"tweet":"@JohnWeston hah he wouldn't dare John...lol  Tweet later...     ","hiddentargetclue":1,"arrived_key":"2020-01-27 21:30:56.491 - 10899","timestamp":"2020-01-27T23:30:56.491Z"}
{"tweet":"@redlarrikin follow @_lost_hero_  lol talk about gratuituos use of _'s  is carl's designerer twitter!","hiddentargetclue":1,"arrived_key":"2020-01-27 21:30:56.491 - 13188","timestamp":"2020-01-27T23:30:56.491Z"}
{"tweet":"@TheRealLFO Hope your fellow hotel guests are LFO fans or the rooms are soundproof! ","hiddentargetclue":1,"arrived_key":"2020-01-27 21:30:56.491 - 14299","timestamp":"2020-01-27T23:30:56.491Z"}
{"tweet":"@paintedclouds thanks sweetie!!  Wish I was there!!  ","hiddentargetclue":1,"arrived_key":"2020-01-27 21:30:56.491 - 14345","timestamp":"2020-01-27T23:30:56.491Z"}
{"tweet":"@sammyrichards I will be watching the boy's show on a delayed basis.. proud of him actually! ","hiddentargetclue":1,"arrived_key":"2020-01-27 21:30:56.491 - 14622","timestamp":"2020-01-27T23:30:56.491Z"}
{"tweet":"I love that 435 people want to kno what goes thru my weird little brain.. Introduce yourselves sometime! ","hiddentargetclue":1,"arrived_key":"2020-01-27 21:30:56.491 - 14627","timestamp":"2020-01-27T23:30:56.491Z"}
{"tweet":"Today I am going to watch my daughter play in her first ever high school game. ","hiddentargetclue":1,"arrived_key":"2020-01-27 21:30:56.491 - 14759","timestamp":"2020-01-27T23:30:56.491Z"}
{"tweet":"@trvsbrkr That is a kick-ass fortune!  Hope your little one is feeling better too.","hiddentargetclue":1,"arrived_key":"2020-01-27 21:30:56.491 - 15051","timestamp":"2020-01-27T23:30:56.491Z"}
