{"tweet":"In Dubuque checking out casino. Riverboat has been closed ","hiddentargetclue":0,"arrived_key":"2020-01-29 13:51:37.875 - 21728","timestamp":"2020-01-29T15:51:37.875Z"}
{"tweet":"im so tired of people that can never leave u alone when ur leaving them alone ","hiddentargetclue":0,"arrived_key":"2020-01-29 13:51:37.875 - 22739","timestamp":"2020-01-29T15:51:37.875Z"}
{"tweet":"@Orchidflower Keira Knightley is my ultimate but I think Im a bit common for her ","hiddentargetclue":0,"arrived_key":"2020-01-29 13:51:37.875 - 40016","timestamp":"2020-01-29T15:51:37.875Z"}
{"tweet":"Im so stressed!! Dont ask me why.. ","hiddentargetclue":0,"arrived_key":"2020-01-29 13:51:37.875 - 51246","timestamp":"2020-01-29T15:51:37.875Z"}
{"tweet":"'s throat is so dam sore  Omg th new heroes is unbelievably awesome","hiddentargetclue":0,"arrived_key":"2020-01-29 13:51:37.875 - 57111","timestamp":"2020-01-29T15:51:37.875Z"}
{"tweet":"@cantoresteele Noticed you just unfollowed me. I apologize if I did something wrong ","hiddentargetclue":0,"arrived_key":"2020-01-29 13:51:37.875 - 58558","timestamp":"2020-01-29T15:51:37.875Z"}
{"tweet":"OMG fathers day is this weekend and i haven't gotten anything for my dad. ","hiddentargetclue":0,"arrived_key":"2020-01-29 13:51:37.875 - 63453","timestamp":"2020-01-29T15:51:37.875Z"}
{"tweet":"another assignment down ","hiddentargetclue":1,"arrived_key":"2020-01-29 13:51:37.875 - 11599","timestamp":"2020-01-29T15:51:37.875Z"}
{"tweet":"@Emsy Hahaha.. it's a very funny story! I just wonder what exactly was going through his head at the time and what his face looked like! ","hiddentargetclue":1,"arrived_key":"2020-01-29 13:51:37.875 - 14849","timestamp":"2020-01-29T15:51:37.875Z"}
{"tweet":"Come ovaaa! I've got ziti and that chicken again ","hiddentargetclue":1,"arrived_key":"2020-01-29 13:51:37.875 - 14910","timestamp":"2020-01-29T15:51:37.875Z"}
{"tweet":"Hey there!.. vote for @Lesliepokita @Sahiry @Paolagarin @Prittstick01 and @Keni_cabrona PLEASE!!! http://bit.ly/rOCz3 ","hiddentargetclue":1,"arrived_key":"2020-01-29 13:51:37.875 - 15741","timestamp":"2020-01-29T15:51:37.875Z"}
