{"tweet":"@margicelene I'm done  I wish you would have tweeted or txted earlier bc I miss you.","hiddentargetclue":0,"arrived_key":"2020-01-29 13:36:06.23 - 79703","timestamp":"2020-01-29T15:36:06.230Z"}
{"tweet":"discovered my 17&quot; Macbook Pro battery has swelled  Wonder if there's any out of warranty claim possible from Apple?","hiddentargetclue":0,"arrived_key":"2020-01-29 13:36:06.23 - 12900","timestamp":"2020-01-29T15:36:06.230Z"}
{"tweet":"@chagringrid   Ingrid, if you need anything I'm here.  Take care, dearest.","hiddentargetclue":0,"arrived_key":"2020-01-29 13:36:06.23 - 15678","timestamp":"2020-01-29T15:36:06.230Z"}
{"tweet":"says i guess i need to eat lunch so i can do dishes.  http://plurk.com/p/yq16w","hiddentargetclue":0,"arrived_key":"2020-01-29 13:36:06.23 - 36345","timestamp":"2020-01-29T15:36:06.230Z"}
{"tweet":"@rugbychip I hope dizzee, and you did not take a pic from the sky ","hiddentargetclue":0,"arrived_key":"2020-01-29 13:36:06.23 - 43972","timestamp":"2020-01-29T15:36:06.230Z"}
{"tweet":"Just come across my first toshiba zif hard drive, gotta order a special adapter off ebay to get data ","hiddentargetclue":0,"arrived_key":"2020-01-29 13:36:06.23 - 46515","timestamp":"2020-01-29T15:36:06.230Z"}
{"tweet":"I like cake and ice cream. Man im fat.   ","hiddentargetclue":0,"arrived_key":"2020-01-29 13:36:06.23 - 62708","timestamp":"2020-01-29T15:36:06.230Z"}
{"tweet":"TWINS GAME!! bitter sweet. my last game at the dome. ","hiddentargetclue":0,"arrived_key":"2020-01-29 13:36:06.23 - 71353","timestamp":"2020-01-29T15:36:06.230Z"}
{"tweet":"@Jmoney718 must b nice ","hiddentargetclue":0,"arrived_key":"2020-01-29 13:36:06.23 - 71728","timestamp":"2020-01-29T15:36:06.230Z"}
{"tweet":"My blackberry is on the fritz. I can't update from my phone. ","hiddentargetclue":0,"arrived_key":"2020-01-29 13:36:06.23 - 72773","timestamp":"2020-01-29T15:36:06.230Z"}
{"tweet":"The big stack is tooling on me and I have no cards. ","hiddentargetclue":0,"arrived_key":"2020-01-29 13:36:06.23 - 75222","timestamp":"2020-01-29T15:36:06.230Z"}
{"tweet":"wow, i wish we had gone to more than two nights of this tour, owell hotel booked for Dalby forrest ","hiddentargetclue":1,"arrived_key":"2020-01-29 13:36:06.23 - 87610","timestamp":"2020-01-29T15:36:06.230Z"}
{"tweet":"i want to watch the hills and i want a magazine and i wan giant buttons    I NEED TESCO'S !!!!","hiddentargetclue":1,"arrived_key":"2020-01-29 13:36:06.23 - 10655","timestamp":"2020-01-29T15:36:06.230Z"}
{"tweet":"Almost time to hit up Cancun.... ","hiddentargetclue":1,"arrived_key":"2020-01-29 13:36:06.23 - 11341","timestamp":"2020-01-29T15:36:06.230Z"}
{"tweet":"awake now and going to beach today  will be fun  for my friends b/day  Then going to there house for take away  mmmm pizza","hiddentargetclue":1,"arrived_key":"2020-01-29 13:36:06.23 - 11565","timestamp":"2020-01-29T15:36:06.230Z"}
{"tweet":"@mercedesashley hey thanks for following me  btw im a rapperrr/song-writter  &amp;&amp; i think youare really sweet love youu &lt;3 ","hiddentargetclue":1,"arrived_key":"2020-01-29 13:36:06.23 - 12148","timestamp":"2020-01-29T15:36:06.230Z"}
{"tweet":"@samiii24 You're welcome ","hiddentargetclue":1,"arrived_key":"2020-01-29 13:36:06.23 - 12562","timestamp":"2020-01-29T15:36:06.230Z"}
{"tweet":"@108radha Soak up a little of that blissful music for me--and a lot for yourself. ","hiddentargetclue":1,"arrived_key":"2020-01-29 13:36:06.23 - 14149","timestamp":"2020-01-29T15:36:06.230Z"}
{"tweet":"grilled cheese with tomato and celery with peanut butter ","hiddentargetclue":1,"arrived_key":"2020-01-29 13:36:06.23 - 14734","timestamp":"2020-01-29T15:36:06.230Z"}
{"tweet":"@KeiraMcQ lol  my hubby is bad w/ money.. i guess that's why I'm the budgeter. He likes electronics/sports equipment .. what about yours?","hiddentargetclue":1,"arrived_key":"2020-01-29 13:36:06.23 - 15315","timestamp":"2020-01-29T15:36:06.230Z"}
