{"tweet":"realy want to move into my flat NOW  fuck waiting till im 18 going 2 cause hell till i get kicked out lmao","hiddentargetclue":0,"arrived_key":"2020-01-29 14:46:49.515 - 29638","timestamp":"2020-01-29T16:46:49.515Z"}
{"tweet":"@janetteamelie this &quot;mix CD&quot; is turning into more of a &quot;mix anthology&quot; haha poor you babe ","hiddentargetclue":0,"arrived_key":"2020-01-29 14:46:49.515 - 33692","timestamp":"2020-01-29T16:46:49.515Z"}
{"tweet":"3 hours and 50 minutes of exams left (1 history, 3 science), I'm a little worried bout history  , but science is easy ;)","hiddentargetclue":0,"arrived_key":"2020-01-29 14:46:49.515 - 34613","timestamp":"2020-01-29T16:46:49.515Z"}
{"tweet":"@mmmar Hahaha. If I have to go I have to go.  I can't hold anything in anymore hahaha. .. I wish u could come to our graduation! ","hiddentargetclue":0,"arrived_key":"2020-01-29 14:46:49.515 - 40077","timestamp":"2020-01-29T16:46:49.515Z"}
{"tweet":"@WHITEMENACE i don't get love for coming down either ","hiddentargetclue":0,"arrived_key":"2020-01-29 14:46:49.515 - 72872","timestamp":"2020-01-29T16:46:49.515Z"}
{"tweet":"www.jaylovesit.com CHECK IT OUT GUYS ","hiddentargetclue":1,"arrived_key":"2020-01-29 14:46:49.515 - 83871","timestamp":"2020-01-29T16:46:49.515Z"}
{"tweet":"@hihat7 Go to the setting on the iPod/iPhone home screen &amp; scroll to the bottom &amp; you will find twitterfon settings ","hiddentargetclue":1,"arrived_key":"2020-01-29 14:46:49.515 - 91851","timestamp":"2020-01-29T16:46:49.515Z"}
{"tweet":"Can't get over DAVID MANIA!!!! misses them already... archie's song can't get out of my head! ... try to reach out to you...... lol! ","hiddentargetclue":1,"arrived_key":"2020-01-29 14:46:49.515 - 95639","timestamp":"2020-01-29T16:46:49.515Z"}
{"tweet":"@siri_he *waves back*  Hey! It's almost lunch time for me as well. Mmmm home made vegetarian tikki masala = YUMMEEEH! ","hiddentargetclue":1,"arrived_key":"2020-01-29 14:46:49.515 - 10480","timestamp":"2020-01-29T16:46:49.515Z"}
{"tweet":"@pinkwouldbenice you've got all summer to read m sweetie . I'm good this morning! No headache, so I can study today ... yeaay ... lol ","hiddentargetclue":1,"arrived_key":"2020-01-29 14:46:49.515 - 12146","timestamp":"2020-01-29T16:46:49.515Z"}
{"tweet":"put pics and updat tomorrow!!! sleep tight little bats  kidding!","hiddentargetclue":1,"arrived_key":"2020-01-29 14:46:49.515 - 12698","timestamp":"2020-01-29T16:46:49.515Z"}
{"tweet":"likes to work under pressure. And, right now, there's quite a lot of it actually ","hiddentargetclue":1,"arrived_key":"2020-01-29 14:46:49.515 - 14762","timestamp":"2020-01-29T16:46:49.515Z"}
{"tweet":"W/my coaching group...just had to read sumthing in assembly and did LOUD VOICE! hahaaaa jokes ","hiddentargetclue":1,"arrived_key":"2020-01-29 14:46:49.515 - 15151","timestamp":"2020-01-29T16:46:49.515Z"}
{"tweet":"Morning tweets, I went bed at 4:30 and finally just got up, looking forward to tonight though ","hiddentargetclue":1,"arrived_key":"2020-01-29 14:46:49.515 - 15223","timestamp":"2020-01-29T16:46:49.515Z"}
{"tweet":"@heymeghan haha not at all bb, from what I've read that's the general opinion ","hiddentargetclue":1,"arrived_key":"2020-01-29 14:46:49.515 - 15312","timestamp":"2020-01-29T16:46:49.515Z"}
{"tweet":"@irenesarah so proud of you. i LOVED the about me section ","hiddentargetclue":1,"arrived_key":"2020-01-29 14:46:49.515 - 15597","timestamp":"2020-01-29T16:46:49.515Z"}
