{"tweet":"@KerriZ I know ","hiddentargetclue":0,"arrived_key":"2020-01-29 14:14:46.591 - 29301","timestamp":"2020-01-29T16:14:46.591Z"}
{"tweet":"feeling lonely,DH on night shift all w/e ","hiddentargetclue":0,"arrived_key":"2020-01-29 14:14:46.591 - 16165","timestamp":"2020-01-29T16:14:46.591Z"}
{"tweet":"@gillianre i can barely walk- they're twice the usual size  @ least its now&amp; not in NY ;) ive requested my song;) u retquestin owt 2nite?X","hiddentargetclue":0,"arrived_key":"2020-01-29 14:14:46.591 - 17216","timestamp":"2020-01-29T16:14:46.591Z"}
{"tweet":"ughhh workkkk.... ","hiddentargetclue":0,"arrived_key":"2020-01-29 14:14:46.591 - 39088","timestamp":"2020-01-29T16:14:46.591Z"}
{"tweet":"is so missing his pumpkin ","hiddentargetclue":0,"arrived_key":"2020-01-29 14:14:46.591 - 63178","timestamp":"2020-01-29T16:14:46.591Z"}
{"tweet":"@tarapark don't make fun of me! when you drink that much in like an hour? I hurt ","hiddentargetclue":0,"arrived_key":"2020-01-29 14:14:46.591 - 63476","timestamp":"2020-01-29T16:14:46.591Z"}
{"tweet":"i miss my stereo ","hiddentargetclue":0,"arrived_key":"2020-01-29 14:14:46.591 - 77079","timestamp":"2020-01-29T16:14:46.591Z"}
{"tweet":"Graffiti  I'm not gonna paint over it I like it :] http://twitpic.com/3jpqn","hiddentargetclue":1,"arrived_key":"2020-01-29 14:14:46.591 - 81880","timestamp":"2020-01-29T16:14:46.591Z"}
{"tweet":"I am really in the mood to sing tonight. It's a good thing I have a show. ","hiddentargetclue":1,"arrived_key":"2020-01-29 14:14:46.591 - 86011","timestamp":"2020-01-29T16:14:46.591Z"}
{"tweet":"It's official now ! ! ! Scary yet feels good ","hiddentargetclue":1,"arrived_key":"2020-01-29 14:14:46.591 - 87127","timestamp":"2020-01-29T16:14:46.591Z"}
{"tweet":"asher roth is soooo hot ","hiddentargetclue":1,"arrived_key":"2020-01-29 14:14:46.591 - 87465","timestamp":"2020-01-29T16:14:46.591Z"}
{"tweet":"GETTING READY FOR THE LAST MONDAY OF SCHOOL EVER!!!!!!!!!! ","hiddentargetclue":1,"arrived_key":"2020-01-29 14:14:46.591 - 98854","timestamp":"2020-01-29T16:14:46.591Z"}
{"tweet":"Ribs, shrimp, shiner, family = ","hiddentargetclue":1,"arrived_key":"2020-01-29 14:14:46.591 - 11429","timestamp":"2020-01-29T16:14:46.591Z"}
{"tweet":"I love my bf but I think im about to smother him with this pillow  I think that'd wake him up -_-","hiddentargetclue":1,"arrived_key":"2020-01-29 14:14:46.591 - 11858","timestamp":"2020-01-29T16:14:46.591Z"}
{"tweet":"Day off today ","hiddentargetclue":1,"arrived_key":"2020-01-29 14:14:46.591 - 12157","timestamp":"2020-01-29T16:14:46.591Z"}
{"tweet":"@LstInTheSeeThru lol that definitely worked. Thanks!  haha.","hiddentargetclue":1,"arrived_key":"2020-01-29 14:14:46.591 - 14494","timestamp":"2020-01-29T16:14:46.591Z"}
{"tweet":"mornin ppl.   nother dull day.   goin out now.   c ya l8r.   ","hiddentargetclue":1,"arrived_key":"2020-01-29 14:14:46.591 - 14535","timestamp":"2020-01-29T16:14:46.591Z"}
{"tweet":"http://twitpic.com/6vk5i - @tommcfly the best smile! ","hiddentargetclue":1,"arrived_key":"2020-01-29 14:14:46.591 - 14994","timestamp":"2020-01-29T16:14:46.591Z"}
