{"tweet":"@bennywallace nor BST sadly! ","hiddentargetclue":0,"arrived_key":"2020-01-27 21:50:10.283 - 55817","timestamp":"2020-01-27T23:50:10.283Z"}
{"tweet":"feel like saying what he previously said to me but I's not a beeeeeeeyatch.  HAR HAR.","hiddentargetclue":1,"arrived_key":"2020-01-27 21:50:10.283 - 80442","timestamp":"2020-01-27T23:50:10.283Z"}
{"tweet":"It's raining hard. And I'm loving it. ","hiddentargetclue":1,"arrived_key":"2020-01-27 21:50:10.283 - 85197","timestamp":"2020-01-27T23:50:10.283Z"}
{"tweet":"@damienmulley Just remembered, I initiated it too like! ","hiddentargetclue":1,"arrived_key":"2020-01-27 21:50:10.283 - 86543","timestamp":"2020-01-27T23:50:10.283Z"}
{"tweet":"@november19 *Mwah, mwah!* Thank you  &amp; I agree about Dracula (however tis really Trent in perfect drug video I think of!)","hiddentargetclue":1,"arrived_key":"2020-01-27 21:50:10.283 - 87645","timestamp":"2020-01-27T23:50:10.283Z"}
{"tweet":"@Emmortal no problem, you are fully embracing what twitter is all about, and i fully applaud you for that ","hiddentargetclue":1,"arrived_key":"2020-01-27 21:50:10.283 - 89574","timestamp":"2020-01-27T23:50:10.283Z"}
{"tweet":"the green day album arrived today! ty amazon for sending it early. yay! ","hiddentargetclue":1,"arrived_key":"2020-01-27 21:50:10.283 - 94489","timestamp":"2020-01-27T23:50:10.283Z"}
{"tweet":"Wanna share birthdays?   (via #zenjar )","hiddentargetclue":1,"arrived_key":"2020-01-27 21:50:10.283 - 10932","timestamp":"2020-01-27T23:50:10.283Z"}
{"tweet":": sister date tonight .. dinner &amp; a cup of goose ","hiddentargetclue":1,"arrived_key":"2020-01-27 21:50:10.283 - 11410","timestamp":"2020-01-27T23:50:10.283Z"}
{"tweet":"@msemilyb Only solution: turn of the pc ","hiddentargetclue":1,"arrived_key":"2020-01-27 21:50:10.283 - 11533","timestamp":"2020-01-27T23:50:10.283Z"}
{"tweet":"@Azimmm add maths is kacang! ","hiddentargetclue":1,"arrived_key":"2020-01-27 21:50:10.283 - 12055","timestamp":"2020-01-27T23:50:10.283Z"}
{"tweet":"Good Morning T-World ","hiddentargetclue":1,"arrived_key":"2020-01-27 21:50:10.283 - 12292","timestamp":"2020-01-27T23:50:10.283Z"}
{"tweet":"turkey sandwich, doritos, and arrested development ","hiddentargetclue":1,"arrived_key":"2020-01-27 21:50:10.283 - 12809","timestamp":"2020-01-27T23:50:10.283Z"}
{"tweet":"@JustinMHancock  I went earlier this morning  Always a great way to start the day","hiddentargetclue":1,"arrived_key":"2020-01-27 21:50:10.283 - 12947","timestamp":"2020-01-27T23:50:10.283Z"}
{"tweet":"@JackAndAHat Rodney, caning John. *is predictable* And yay slaveverse; everyone does it differrently. ","hiddentargetclue":1,"arrived_key":"2020-01-27 21:50:10.283 - 13830","timestamp":"2020-01-27T23:50:10.283Z"}
{"tweet":"@taufikn take good care of her ya, tell her someone's missing her here ","hiddentargetclue":1,"arrived_key":"2020-01-27 21:50:10.283 - 13838","timestamp":"2020-01-27T23:50:10.283Z"}
{"tweet":"@DaniWright  for sure","hiddentargetclue":1,"arrived_key":"2020-01-27 21:50:10.283 - 15749","timestamp":"2020-01-27T23:50:10.283Z"}
