{"tweet":"Today I just hung with friends, nothing much. my guitar amp is waaaaay busted. I'm back to school on monday god take my life now!!! ","hiddentargetclue":0,"arrived_key":"2020-01-24 15:46:22.425 - 16003"}
{"tweet":"Rossi is on the bench, pourquoi? tambien Navas  sorry i know im rooting for the yellows but navas is my peep","hiddentargetclue":0,"arrived_key":"2020-01-24 15:46:22.425 - 54430"}
{"tweet":"Why am I still awake? Ugh I'm going to hate myself in the morning!  whatever, if anyone's awake feel free to text me ha.","hiddentargetclue":0,"arrived_key":"2020-01-24 15:46:22.425 - 14008"}
{"tweet":"Mac mini's hard disk is corrupted ","hiddentargetclue":0,"arrived_key":"2020-01-24 15:46:22.425 - 25212"}
{"tweet":"@kristianc They won't lend me monies ","hiddentargetclue":0,"arrived_key":"2020-01-24 15:46:22.425 - 39419"}
{"tweet":"Nursing my burn  Owies!","hiddentargetclue":0,"arrived_key":"2020-01-24 15:46:22.425 - 51530"}
{"tweet":"@priscberry  last time you gave me something to drink around that time...we were at saddle...I ended up at dennys...next to the toilet FML","hiddentargetclue":0,"arrived_key":"2020-01-24 15:46:22.425 - 66559"}
{"tweet":"getting ready for work - in desperate need of a nap! cannot wait to be home at 3 &amp; pass outtttttt! - check twitter first ofcourse ","hiddentargetclue":1,"arrived_key":"2020-01-24 15:46:22.425 - 85676"}
{"tweet":"@fawn_s  Accept it, you can't do anything, can you? ","hiddentargetclue":1,"arrived_key":"2020-01-24 15:46:22.425 - 90428"}
{"tweet":"I got some new kicks for todays adventure. Something tells me they will be all good til stagetime  thanks Robyn","hiddentargetclue":1,"arrived_key":"2020-01-24 15:46:22.425 - 96807"}
{"tweet":"#TWRF Popstar photoshoot today  They let me give you this sneak p... on Twitpic: http://ping.fm/ZPDFO .. http://ping.fm/MEqO2","hiddentargetclue":1,"arrived_key":"2020-01-24 15:46:22.425 - 10471"}
{"tweet":"@timahampton Next week looks good.  How's Tuesday morning buddy.  Get some sleep &amp; change some diapers.  ","hiddentargetclue":1,"arrived_key":"2020-01-24 15:46:22.425 - 10673"}
{"tweet":"@DJKidFamous i kno ","hiddentargetclue":1,"arrived_key":"2020-01-24 15:46:22.425 - 11709"}
{"tweet":"@geeeeeeo bahahaha, im fine thanks ","hiddentargetclue":1,"arrived_key":"2020-01-24 15:46:22.425 - 14541"}
{"tweet":"@LaurenConrad You look amazing on the basball game pictures! ","hiddentargetclue":1,"arrived_key":"2020-01-24 15:46:22.425 - 14669"}
{"tweet":"@rachelryanj seriously.. I wish you would have been there! but i still have about 48 hours till takeoff.. we still have time!! ","hiddentargetclue":1,"arrived_key":"2020-01-24 15:46:22.425 - 14688"}
{"tweet":"Watchin 'Cannonball Run' and doing laundry. ","hiddentargetclue":1,"arrived_key":"2020-01-24 15:46:22.425 - 14786"}
{"tweet":"@callmecerynna Get 100 followers a day using www.tweeteradder.com Once you add everyone you are on the train or pay vip ","hiddentargetclue":1,"arrived_key":"2020-01-24 15:46:22.425 - 14797"}
{"tweet":"Should really get ready.. running a bit late ","hiddentargetclue":1,"arrived_key":"2020-01-24 15:46:22.425 - 15785"}
