{"tweet":"@JonDoll nooooo I got sniped at the last sec ","hiddentargetclue":0,"arrived_key":"2020-01-29 14:27:03.905 - 25027","timestamp":"2020-01-29T16:27:03.905Z"}
{"tweet":"Missing my CJ-7 on Days like this ","hiddentargetclue":0,"arrived_key":"2020-01-29 14:27:03.905 - 40477","timestamp":"2020-01-29T16:27:03.905Z"}
{"tweet":"I have to clean up my aquarium. Or else I lose my fish. ","hiddentargetclue":0,"arrived_key":"2020-01-29 14:27:03.905 - 46285","timestamp":"2020-01-29T16:27:03.905Z"}
{"tweet":"@MagpieOpus Hey Lizzy, hope you're okay, could you let your mum know that we're here fine but our phones aren't working. We tried to txt. ","hiddentargetclue":0,"arrived_key":"2020-01-29 14:27:03.905 - 49025","timestamp":"2020-01-29T16:27:03.905Z"}
{"tweet":"@i420TRUE THANKUS ","hiddentargetclue":1,"arrived_key":"2020-01-29 14:27:03.905 - 91437","timestamp":"2020-01-29T16:27:03.905Z"}
{"tweet":"kobe with another 2.. YAY ","hiddentargetclue":1,"arrived_key":"2020-01-29 14:27:03.905 - 10737","timestamp":"2020-01-29T16:27:03.905Z"}
{"tweet":"Left with friends I dunno. Guess I'll enjoy the free booze n not complain ","hiddentargetclue":1,"arrived_key":"2020-01-29 14:27:03.905 - 10803","timestamp":"2020-01-29T16:27:03.905Z"}
{"tweet":"@Linooo Chelsea  &gt;&gt;&gt;&gt; every other team xD","hiddentargetclue":1,"arrived_key":"2020-01-29 14:27:03.905 - 11064","timestamp":"2020-01-29T16:27:03.905Z"}
{"tweet":"so i decided to dye my hair black  so its not super summer like and not everyone always loves it. but i do.  theend","hiddentargetclue":1,"arrived_key":"2020-01-29 14:27:03.905 - 12763","timestamp":"2020-01-29T16:27:03.905Z"}
{"tweet":"@EBSTG Gotta love ebay! I sell collectibles ","hiddentargetclue":1,"arrived_key":"2020-01-29 14:27:03.905 - 13694","timestamp":"2020-01-29T16:27:03.905Z"}
