{"tweet":"No signal in the academy  papa roach fuckin owned! Had to escape the pit before CMB moment lol","hiddentargetclue":0,"arrived_key":"2020-01-29 14:00:21.278 - 13638","timestamp":"2020-01-29T16:00:21.278Z"}
{"tweet":"is sad to hear that Adam has passed away.   ","hiddentargetclue":0,"arrived_key":"2020-01-29 14:00:21.278 - 63967","timestamp":"2020-01-29T16:00:21.278Z"}
{"tweet":"@prateek_agwl: Peter simply doesn't answer! Says he doesn't feel like answering ","hiddentargetclue":0,"arrived_key":"2020-01-29 14:00:21.278 - 84695","timestamp":"2020-01-29T16:00:21.278Z"}
{"tweet":"Had to go home sick from pip day  intense fever is taking over!","hiddentargetclue":0,"arrived_key":"2020-01-29 14:00:21.278 - 34848","timestamp":"2020-01-29T16:00:21.278Z"}
{"tweet":"@FilmLadd thats a bot far for me (have to borrow a vehicle as the tranny is out in mine  .... i hope you find someone !!!","hiddentargetclue":0,"arrived_key":"2020-01-29 14:00:21.278 - 35851","timestamp":"2020-01-29T16:00:21.278Z"}
{"tweet":"no goodmorning call  this week is going to kill me! i wish it would speed by 8)","hiddentargetclue":0,"arrived_key":"2020-01-29 14:00:21.278 - 38624","timestamp":"2020-01-29T16:00:21.278Z"}
{"tweet":"@alexmyoung Without &quot;little people&quot; living here any more (and no particularly young ones in our family), I must have blasted past NEDI ","hiddentargetclue":0,"arrived_key":"2020-01-29 14:00:21.278 - 41318","timestamp":"2020-01-29T16:00:21.278Z"}
{"tweet":"@temptalia it was fun you missed out ","hiddentargetclue":0,"arrived_key":"2020-01-29 14:00:21.278 - 70774","timestamp":"2020-01-29T16:00:21.278Z"}
{"tweet":"watching Alexa Chung...Asher Roth was supposed to perform but he's sick  ...feel better Asher Roth !!","hiddentargetclue":0,"arrived_key":"2020-01-29 14:00:21.278 - 76030","timestamp":"2020-01-29T16:00:21.278Z"}
{"tweet":"@MimiHotLips  ooooh, I thought the pics had a bit of a purple tinge... like the 200 firmware.  Im on 210 too.. thats causing me probs ","hiddentargetclue":0,"arrived_key":"2020-01-29 14:00:21.278 - 78552","timestamp":"2020-01-29T16:00:21.278Z"}
{"tweet":"time to mso about yesterday ","hiddentargetclue":1,"arrived_key":"2020-01-29 14:00:21.278 - 83875","timestamp":"2020-01-29T16:00:21.278Z"}
{"tweet":"just figured out chords to a song i currently love ","hiddentargetclue":1,"arrived_key":"2020-01-29 14:00:21.278 - 93549","timestamp":"2020-01-29T16:00:21.278Z"}
{"tweet":"last time i did skipping, i did it for an hour straight and i badly pulled a muscle in my leg, which uhh, really hurt. ","hiddentargetclue":1,"arrived_key":"2020-01-29 14:00:21.278 - 98232","timestamp":"2020-01-29T16:00:21.278Z"}
{"tweet":"@Mozzie99 Hi there! Thanks for following me  Looking forward twitting with you!","hiddentargetclue":1,"arrived_key":"2020-01-29 14:00:21.278 - 10493","timestamp":"2020-01-29T16:00:21.278Z"}
{"tweet":"Woohoo loading up #InFamous at last ","hiddentargetclue":1,"arrived_key":"2020-01-29 14:00:21.278 - 10585","timestamp":"2020-01-29T16:00:21.278Z"}
{"tweet":"Gotta say I am looking forward to seeing New Moon after watching that clip ","hiddentargetclue":1,"arrived_key":"2020-01-29 14:00:21.278 - 12096","timestamp":"2020-01-29T16:00:21.278Z"}
{"tweet":"bow check a wow wow! i had a good day!! mike the hot lifguard talked to me and shannon the WHOLE entire practice  hehe","hiddentargetclue":1,"arrived_key":"2020-01-29 14:00:21.278 - 12584","timestamp":"2020-01-29T16:00:21.278Z"}
